{
  "DISCLAIMER": "Under construction, use the results with caution.",
  "14-Apr-2026_Tue_21-25-50.756160": "InputManager.get_data() called for ['animal', 'herd_information', 'calf_num'].",
  "14-Apr-2026_Tue_21-25-50.756213": "InputManager.get_data() called for ['animal', 'pen_information', '0', 'animal_combination'].",
  "14-Apr-2026_Tue_21-25-50.756228": "InputManager.get_data() called for ['animal', 'pen_information', '0', 'number_of_stalls'].",
  "14-Apr-2026_Tue_21-25-50.756240": "InputManager.get_data() called for ['animal', 'pen_information', '0', 'max_stocking_density'].",
  "14-Apr-2026_Tue_21-25-50.756385": "InputManager.get_data() called for ['animal', 'herd_information', 'heiferI_num'].",
  "14-Apr-2026_Tue_21-25-50.756399": "InputManager.get_data() called for ['animal', 'herd_information', 'heiferII_num'].",
  "14-Apr-2026_Tue_21-25-50.756412": "InputManager.get_data() called for ['animal', 'pen_information', '1', 'animal_combination'].",
  "14-Apr-2026_Tue_21-25-50.756426": "InputManager.get_data() called for ['animal', 'pen_information', '1', 'number_of_stalls'].",
  "14-Apr-2026_Tue_21-25-50.756437": "InputManager.get_data() called for ['animal', 'pen_information', '1', 'max_stocking_density'].",
  "14-Apr-2026_Tue_21-25-50.756482": "InputManager.get_data() called for ['animal', 'herd_information', 'parity_fractions', '1'].",
  "14-Apr-2026_Tue_21-25-50.756494": "InputManager.get_data() called for ['animal', 'herd_information', 'parity_fractions', '2'].",
  "14-Apr-2026_Tue_21-25-50.756505": "InputManager.get_data() called for ['animal', 'herd_information', 'parity_fractions', '3'].",
  "14-Apr-2026_Tue_21-25-50.756515": "InputManager.get_data() called for ['animal', 'herd_information', 'parity_fractions', '4'].",
  "14-Apr-2026_Tue_21-25-50.756525": "InputManager.get_data() called for ['animal', 'herd_information', 'parity_fractions', '5'].",
  "14-Apr-2026_Tue_21-25-50.786499": "InputManager.get_data() called for ['config'].",
  "14-Apr-2026_Tue_21-25-50.787737": "InputManager.get_data() called for ['animal', 'herd_information', 'breed'].",
  "14-Apr-2026_Tue_21-25-50.787782": "InputManager.get_data() called for ['animal', 'animal_config', 'farm_level', 'repro', 'calving_interval'].",
  "14-Apr-2026_Tue_21-25-50.787801": "InputManager.get_data() called for ['animal', 'herd_initialization', 'initial_animal_num'].",
  "14-Apr-2026_Tue_21-25-50.787817": "InputManager.get_data() called for ['animal', 'herd_initialization', 'simulation_days'].",
  "14-Apr-2026_Tue_21-25-50.787867": "InputManager.get_data() called for ['animal_net_merit'].",
  "14-Apr-2026_Tue_21-25-50.787965": "InputManager.get_data() called for ['animal_top_listing_semen'].",
  "14-Apr-2026_Tue_21-25-50.789289": "InputManager.get_data() called for ['animal'].",
  "14-Apr-2026_Tue_21-25-50.789699": "InputManager.get_data() called for ['feed', 'milk_reduction_maximum'].",
  "14-Apr-2026_Tue_21-25-50.789779": "InputManager.get_data() called for ['lactation'].",
  "14-Apr-2026_Tue_21-25-50.790080": "InputManager.get_data() called for ['config', 'FIPS_county_code'].",
  "14-Apr-2026_Tue_21-25-50.790099": "InputManager.get_data() called for ['animal'].",
  "14-Apr-2026_Tue_21-25-53.525008": "InputManager.get_data() called for ['animal_population'].",
  "14-Apr-2026_Tue_21-25-55.357945": "InputManager.get_data() called for ['animal', 'herd_information', 'calf_num'].",
  "14-Apr-2026_Tue_21-25-55.379372": "InputManager.get_data() called for ['animal', 'herd_information', 'heiferI_num'].",
  "14-Apr-2026_Tue_21-25-55.437044": "InputManager.get_data() called for ['animal', 'herd_information', 'heiferII_num'].",
  "14-Apr-2026_Tue_21-25-55.493156": "InputManager.get_data() called for ['animal', 'herd_information', 'heiferIII_num_springers'].",
  "14-Apr-2026_Tue_21-25-55.511056": "InputManager.get_data() called for ['animal', 'herd_information', 'replace_num'].",
  "14-Apr-2026_Tue_21-25-56.301831": "InputManager.get_data() called for ['animal', 'herd_information', 'milking_cow_fraction'].",
  "14-Apr-2026_Tue_21-25-56.301923": "InputManager.get_data() called for ['animal', 'herd_information', 'parity_fractions', '1'].",
  "14-Apr-2026_Tue_21-25-56.301939": "InputManager.get_data() called for ['animal', 'herd_information', 'cow_num'].",
  "14-Apr-2026_Tue_21-25-56.351831": "InputManager.get_data() called for ['animal', 'herd_information', 'milking_cow_fraction'].",
  "14-Apr-2026_Tue_21-25-56.351905": "InputManager.get_data() called for ['animal', 'herd_information', 'parity_fractions', '2'].",
  "14-Apr-2026_Tue_21-25-56.351921": "InputManager.get_data() called for ['animal', 'herd_information', 'cow_num'].",
  "14-Apr-2026_Tue_21-25-56.394815": "InputManager.get_data() called for ['animal', 'herd_information', 'milking_cow_fraction'].",
  "14-Apr-2026_Tue_21-25-56.394899": "InputManager.get_data() called for ['animal', 'herd_information', 'parity_fractions', '3'].",
  "14-Apr-2026_Tue_21-25-56.394915": "InputManager.get_data() called for ['animal', 'herd_information', 'cow_num'].",
  "14-Apr-2026_Tue_21-25-56.437295": "InputManager.get_data() called for ['animal', 'herd_information', 'milking_cow_fraction'].",
  "14-Apr-2026_Tue_21-25-56.437356": "InputManager.get_data() called for ['animal', 'herd_information', 'parity_fractions', '4'].",
  "14-Apr-2026_Tue_21-25-56.437387": "InputManager.get_data() called for ['animal', 'herd_information', 'cow_num'].",
  "14-Apr-2026_Tue_21-25-56.469195": "InputManager.get_data() called for ['animal', 'herd_information', 'milking_cow_fraction'].",
  "14-Apr-2026_Tue_21-25-56.469263": "InputManager.get_data() called for ['animal', 'herd_information', 'parity_fractions', '5'].",
  "14-Apr-2026_Tue_21-25-56.469278": "InputManager.get_data() called for ['animal', 'herd_information', 'cow_num'].",
  "14-Apr-2026_Tue_21-25-56.481878": "InputManager.get_data() called for ['animal', 'herd_information', 'milking_cow_fraction'].",
  "14-Apr-2026_Tue_21-25-56.481936": "InputManager.get_data() called for ['animal', 'herd_information', 'parity_fractions', '1'].",
  "14-Apr-2026_Tue_21-25-56.481951": "InputManager.get_data() called for ['animal', 'herd_information', 'cow_num'].",
  "14-Apr-2026_Tue_21-25-56.500817": "InputManager.get_data() called for ['animal', 'herd_information', 'milking_cow_fraction'].",
  "14-Apr-2026_Tue_21-25-56.500875": "InputManager.get_data() called for ['animal', 'herd_information', 'parity_fractions', '2'].",
  "14-Apr-2026_Tue_21-25-56.500889": "InputManager.get_data() called for ['animal', 'herd_information', 'cow_num'].",
  "14-Apr-2026_Tue_21-25-56.520816": "InputManager.get_data() called for ['animal', 'herd_information', 'milking_cow_fraction'].",
  "14-Apr-2026_Tue_21-25-56.520909": "InputManager.get_data() called for ['animal', 'herd_information', 'parity_fractions', '3'].",
  "14-Apr-2026_Tue_21-25-56.520926": "InputManager.get_data() called for ['animal', 'herd_information', 'cow_num'].",
  "14-Apr-2026_Tue_21-25-56.538316": "InputManager.get_data() called for ['animal', 'herd_information', 'milking_cow_fraction'].",
  "14-Apr-2026_Tue_21-25-56.538381": "InputManager.get_data() called for ['animal', 'herd_information', 'parity_fractions', '4'].",
  "14-Apr-2026_Tue_21-25-56.538395": "InputManager.get_data() called for ['animal', 'herd_information', 'cow_num'].",
  "14-Apr-2026_Tue_21-25-56.553437": "InputManager.get_data() called for ['animal', 'herd_information', 'milking_cow_fraction'].",
  "14-Apr-2026_Tue_21-25-56.553570": "InputManager.get_data() called for ['animal', 'herd_information', 'parity_fractions', '5'].",
  "14-Apr-2026_Tue_21-25-56.553589": "InputManager.get_data() called for ['animal', 'herd_information', 'cow_num'].",
  "14-Apr-2026_Tue_21-25-56.747630": "InputManager.get_data() called for ['config'].",
  "14-Apr-2026_Tue_21-25-56.747792": "InputManager.get_data() called for ['weather'].",
  "14-Apr-2026_Tue_21-25-57.069018": "InputManager.get_data() called for ['crop_configurations', 'crop_configurations'].",
  "14-Apr-2026_Tue_21-25-57.069739": "InputManager.get_data() called for ['field Alfalfa 2022'].",
  "14-Apr-2026_Tue_21-25-57.069795": "InputManager.get_data() called for ['soil'].",
  "14-Apr-2026_Tue_21-25-57.070417": "InputManager.get_data() called for ['fertilizer_schedule Alfalfa 2022'].",
  "14-Apr-2026_Tue_21-25-57.070679": "InputManager.get_data() called for ['manure_schedule Alfalfa 2022'].",
  "14-Apr-2026_Tue_21-25-57.070816": "InputManager.get_data() called for ['tillage_schedule Alfalfa 2022'].",
  "14-Apr-2026_Tue_21-25-57.070910": "InputManager.get_data() called for ['crop Alfalfa 2022', 'crop_schedules'].",
  "14-Apr-2026_Tue_21-25-57.071161": "InputManager.get_data() called for ['field Corn 2022'].",
  "14-Apr-2026_Tue_21-25-57.071203": "InputManager.get_data() called for ['soil'].",
  "14-Apr-2026_Tue_21-25-57.071659": "InputManager.get_data() called for ['fertilizer_schedule Corn 2022'].",
  "14-Apr-2026_Tue_21-25-57.071794": "InputManager.get_data() called for ['manure_schedule Corn 2022'].",
  "14-Apr-2026_Tue_21-25-57.071903": "InputManager.get_data() called for ['tillage_schedule Corn 2022'].",
  "14-Apr-2026_Tue_21-25-57.071992": "InputManager.get_data() called for ['crop Corn 2022', 'crop_schedules'].",
  "14-Apr-2026_Tue_21-25-57.072209": "InputManager.get_data() called for ['config', 'nutrient_standard'].",
  "14-Apr-2026_Tue_21-25-57.072227": "InputManager.get_data() called for ['feed'].",
  "14-Apr-2026_Tue_21-25-57.072452": "InputManager.get_data() called for ['feed_storage_configurations'].",
  "14-Apr-2026_Tue_21-25-57.072509": "InputManager.get_data() called for ['feed_storage_instances'].",
  "14-Apr-2026_Tue_21-25-57.072533": "InputManager.get_data() called for ['NASEM_Comp'].",
  "14-Apr-2026_Tue_21-25-57.081482": "InputManager.get_data() called for ['config', 'simulate_animals'].",
  "14-Apr-2026_Tue_21-25-57.081509": "InputManager.get_data() called for ['animal', 'ration', 'formulation_interval'].",
  "14-Apr-2026_Tue_21-25-57.081533": "InputManager.get_data() called for ['animal', 'ration', 'user_input'].",
  "14-Apr-2026_Tue_21-25-57.081545": "InputManager.get_data() called for ['feed', 'max_daily_feed_recalculations_per_year'].",
  "14-Apr-2026_Tue_21-25-57.081573": "InputManager.get_data() called for ['config'].",
  "14-Apr-2026_Tue_21-25-57.081595": "InputManager.get_data() called for ['animal'].",
  "14-Apr-2026_Tue_21-25-57.081869": "InputManager.get_data() called for ['animal'].",
  "14-Apr-2026_Tue_21-25-57.082187": "InputManager.get_data() called for ['feed', 'milk_reduction_maximum'].",
  "14-Apr-2026_Tue_21-25-57.082209": "InputManager.get_data() called for ['lactation'].",
  "14-Apr-2026_Tue_21-25-57.082491": "InputManager.get_data() called for ['config', 'FIPS_county_code'].",
  "14-Apr-2026_Tue_21-25-57.082507": "InputManager.get_data() called for ['animal'].",
  "14-Apr-2026_Tue_21-25-57.509364": "InputManager.get_data() called for ['feed'].",
  "14-Apr-2026_Tue_21-25-57.509767": "InputManager.get_data() called for ['feed', 'allowances'].",
  "14-Apr-2026_Tue_21-25-57.509874": "InputManager.get_data() called for ['animal', 'bedding_configs'].",
  "14-Apr-2026_Tue_21-25-57.509950": "InputManager.get_data() called for ['animal', 'bedding_configs'].",
  "14-Apr-2026_Tue_21-25-57.510007": "InputManager.get_data() called for ['animal', 'bedding_configs'].",
  "14-Apr-2026_Tue_21-25-57.510055": "InputManager.get_data() called for ['animal', 'bedding_configs'].",
  "14-Apr-2026_Tue_21-25-57.547887": "InputManager.get_data() called for ['manure_management'].",
  "14-Apr-2026_Tue_21-25-57.547972": "InputManager.get_data() called for ['manure_processor_connection'].",
  "14-Apr-2026_Tue_21-25-57.548529": "InputManager.get_data() called for ['config', 'FIPS_county_code'].",
  "14-Apr-2026_Tue_21-25-57.548546": "InputManager.get_data() called for ['purchased_feeds_emissions'].",
  "14-Apr-2026_Tue_21-25-57.716238": "InputManager.get_data() called for ['purchased_feed_land_use_change_emissions'].",
  "14-Apr-2026_Tue_21-25-57.878562": "InputManager.get_data() called for ['feed_storage_configurations'].",
  "14-Apr-2026_Tue_21-25-57.878691": "InputManager.get_data() called for ['feed_storage_instances'].",
  "14-Apr-2026_Tue_21-50-00.900351": "InputManager.get_data() called for ['config', 'FIPS_county_code'].",
  "14-Apr-2026_Tue_21-50-00.903145": "InputManager.get_data() called for ['purchased_feeds_emissions'].",
  "14-Apr-2026_Tue_21-50-01.277435": "InputManager.get_data() called for ['purchased_feed_land_use_change_emissions'].",
  "14-Apr-2026_Tue_21-50-02.063380": "InputManager.get_data() called for ['feed_storage_configurations'].",
  "14-Apr-2026_Tue_21-50-02.066111": "InputManager.get_data() called for ['feed_storage_instances'].",
  "14-Apr-2026_Tue_21-50-02.073710": "InputManager.get_data() called for ['config'].",
  "14-Apr-2026_Tue_21-50-13.869043": "InputManager.get_data() called for ['animal', 'herd_information', 'herd_num'].",
  "14-Apr-2026_Tue_21-50-13.871451": "InputManager.get_data() called for ['EEE_constants', 'constants'].",
  "14-Apr-2026_Tue_21-50-13.875530": "InputManager.get_data() called for ['tractor_dataset'].",
  "14-Apr-2026_Tue_21-50-13.882540": "InputManager.get_data() called for ['EEE_constants', 'constants'].",
  "14-Apr-2026_Tue_21-50-13.888014": "InputManager.get_data() called for ['EEE_constants', 'constants'].",
  "14-Apr-2026_Tue_21-50-13.888264": "InputManager.get_data() called for ['tractor_dataset'].",
  "14-Apr-2026_Tue_21-50-13.890884": "InputManager.get_data() called for ['EEE_constants', 'constants'].",
  "14-Apr-2026_Tue_21-50-13.891213": "InputManager.get_data() called for ['EEE_constants', 'constants'].",
  "14-Apr-2026_Tue_21-50-13.891405": "InputManager.get_data() called for ['tractor_dataset'].",
  "14-Apr-2026_Tue_21-50-13.893333": "InputManager.get_data() called for ['EEE_constants', 'constants'].",
  "14-Apr-2026_Tue_21-50-13.893912": "InputManager.get_data() called for ['EEE_constants', 'constants'].",
  "14-Apr-2026_Tue_21-50-13.894125": "InputManager.get_data() called for ['tractor_dataset'].",
  "14-Apr-2026_Tue_21-50-13.896831": "InputManager.get_data() called for ['EEE_constants', 'constants'].",
  "14-Apr-2026_Tue_21-50-13.897128": "InputManager.get_data() called for ['EEE_constants', 'constants'].",
  "14-Apr-2026_Tue_21-50-13.897330": "InputManager.get_data() called for ['tractor_dataset'].",
  "14-Apr-2026_Tue_21-50-13.899233": "InputManager.get_data() called for ['EEE_constants', 'constants'].",
  "14-Apr-2026_Tue_21-50-13.899501": "InputManager.get_data() called for ['EEE_constants', 'constants'].",
  "14-Apr-2026_Tue_21-50-13.899943": "InputManager.get_data() called for ['tractor_dataset'].",
  "14-Apr-2026_Tue_21-50-13.901888": "InputManager.get_data() called for ['EEE_constants', 'constants'].",
  "14-Apr-2026_Tue_21-50-13.902174": "InputManager.get_data() called for ['EEE_constants', 'constants'].",
  "14-Apr-2026_Tue_21-50-13.902369": "InputManager.get_data() called for ['tractor_dataset'].",
  "14-Apr-2026_Tue_21-50-13.904303": "InputManager.get_data() called for ['EEE_constants', 'constants'].",
  "14-Apr-2026_Tue_21-50-13.904586": "InputManager.get_data() called for ['EEE_constants', 'constants'].",
  "14-Apr-2026_Tue_21-50-13.904783": "InputManager.get_data() called for ['tractor_dataset'].",
  "14-Apr-2026_Tue_21-50-13.906830": "InputManager.get_data() called for ['EEE_constants', 'constants'].",
  "14-Apr-2026_Tue_21-50-13.907112": "InputManager.get_data() called for ['EEE_constants', 'constants'].",
  "14-Apr-2026_Tue_21-50-13.907310": "InputManager.get_data() called for ['tractor_dataset'].",
  "14-Apr-2026_Tue_21-50-13.909363": "InputManager.get_data() called for ['EEE_constants', 'constants'].",
  "14-Apr-2026_Tue_21-50-13.909630": "InputManager.get_data() called for ['EEE_constants', 'constants'].",
  "14-Apr-2026_Tue_21-50-13.909827": "InputManager.get_data() called for ['tractor_dataset'].",
  "14-Apr-2026_Tue_21-50-13.911704": "InputManager.get_data() called for ['EEE_constants', 'constants'].",
  "14-Apr-2026_Tue_21-50-13.911961": "InputManager.get_data() called for ['EEE_constants', 'constants'].",
  "14-Apr-2026_Tue_21-50-13.912150": "InputManager.get_data() called for ['tractor_dataset'].",
  "14-Apr-2026_Tue_21-50-13.914199": "InputManager.get_data() called for ['EEE_constants', 'constants'].",
  "14-Apr-2026_Tue_21-50-13.914475": "InputManager.get_data() called for ['EEE_constants', 'constants'].",
  "14-Apr-2026_Tue_21-50-13.914718": "InputManager.get_data() called for ['tractor_dataset'].",
  "14-Apr-2026_Tue_21-50-13.917053": "InputManager.get_data() called for ['EEE_constants', 'constants'].",
  "14-Apr-2026_Tue_21-50-13.917362": "InputManager.get_data() called for ['EEE_constants', 'constants'].",
  "14-Apr-2026_Tue_21-50-13.917560": "InputManager.get_data() called for ['tractor_dataset'].",
  "14-Apr-2026_Tue_21-50-13.919428": "InputManager.get_data() called for ['EEE_constants', 'constants'].",
  "14-Apr-2026_Tue_21-50-13.919666": "InputManager.get_data() called for ['EEE_constants', 'constants'].",
  "14-Apr-2026_Tue_21-50-13.919849": "InputManager.get_data() called for ['tractor_dataset'].",
  "14-Apr-2026_Tue_21-50-13.921732": "InputManager.get_data() called for ['EEE_constants', 'constants'].",
  "14-Apr-2026_Tue_21-50-13.921966": "InputManager.get_data() called for ['EEE_constants', 'constants'].",
  "14-Apr-2026_Tue_21-50-13.922151": "InputManager.get_data() called for ['tractor_dataset'].",
  "14-Apr-2026_Tue_21-50-13.924150": "InputManager.get_data() called for ['EEE_constants', 'constants'].",
  "14-Apr-2026_Tue_21-50-13.924394": "InputManager.get_data() called for ['EEE_constants', 'constants'].",
  "14-Apr-2026_Tue_21-50-13.924576": "InputManager.get_data() called for ['tractor_dataset'].",
  "14-Apr-2026_Tue_21-50-13.926576": "InputManager.get_data() called for ['EEE_constants', 'constants'].",
  "14-Apr-2026_Tue_21-50-13.926832": "InputManager.get_data() called for ['EEE_constants', 'constants'].",
  "14-Apr-2026_Tue_21-50-13.927029": "InputManager.get_data() called for ['tractor_dataset'].",
  "14-Apr-2026_Tue_21-50-13.929047": "InputManager.get_data() called for ['EEE_constants', 'constants'].",
  "14-Apr-2026_Tue_21-50-13.929318": "InputManager.get_data() called for ['EEE_constants', 'constants'].",
  "14-Apr-2026_Tue_21-50-13.929532": "InputManager.get_data() called for ['tractor_dataset'].",
  "14-Apr-2026_Tue_21-50-13.931444": "InputManager.get_data() called for ['EEE_constants', 'constants'].",
  "14-Apr-2026_Tue_21-50-13.931680": "InputManager.get_data() called for ['EEE_constants', 'constants'].",
  "14-Apr-2026_Tue_21-50-13.931861": "InputManager.get_data() called for ['tractor_dataset'].",
  "14-Apr-2026_Tue_21-50-13.933727": "InputManager.get_data() called for ['EEE_constants', 'constants'].",
  "14-Apr-2026_Tue_21-50-13.933963": "InputManager.get_data() called for ['EEE_constants', 'constants'].",
  "14-Apr-2026_Tue_21-50-13.934155": "InputManager.get_data() called for ['tractor_dataset'].",
  "14-Apr-2026_Tue_21-50-13.936101": "InputManager.get_data() called for ['EEE_constants', 'constants'].",
  "14-Apr-2026_Tue_21-50-13.936357": "InputManager.get_data() called for ['EEE_constants', 'constants'].",
  "14-Apr-2026_Tue_21-50-13.936567": "InputManager.get_data() called for ['tractor_dataset'].",
  "14-Apr-2026_Tue_21-50-13.938701": "InputManager.get_data() called for ['EEE_constants', 'constants'].",
  "14-Apr-2026_Tue_21-50-13.938995": "InputManager.get_data() called for ['EEE_constants', 'constants'].",
  "14-Apr-2026_Tue_21-50-13.939213": "InputManager.get_data() called for ['tractor_dataset'].",
  "14-Apr-2026_Tue_21-50-13.941159": "InputManager.get_data() called for ['EEE_constants', 'constants'].",
  "14-Apr-2026_Tue_21-50-13.941409": "InputManager.get_data() called for ['EEE_constants', 'constants'].",
  "14-Apr-2026_Tue_21-50-13.941594": "InputManager.get_data() called for ['tractor_dataset'].",
  "14-Apr-2026_Tue_21-50-13.943773": "InputManager.get_data() called for ['EEE_constants', 'constants'].",
  "14-Apr-2026_Tue_21-50-13.944186": "InputManager.get_data() called for ['EEE_constants', 'constants'].",
  "14-Apr-2026_Tue_21-50-13.944385": "InputManager.get_data() called for ['tractor_dataset'].",
  "14-Apr-2026_Tue_21-50-13.946956": "InputManager.get_data() called for ['EEE_constants', 'constants'].",
  "14-Apr-2026_Tue_21-50-13.947586": "InputManager.get_data() called for ['EEE_constants', 'constants'].",
  "14-Apr-2026_Tue_21-50-13.947827": "InputManager.get_data() called for ['tractor_dataset'].",
  "14-Apr-2026_Tue_21-50-13.951034": "InputManager.get_data() called for ['EEE_constants', 'constants'].",
  "14-Apr-2026_Tue_21-50-13.951451": "InputManager.get_data() called for ['EEE_constants', 'constants'].",
  "14-Apr-2026_Tue_21-50-13.951755": "InputManager.get_data() called for ['tractor_dataset'].",
  "14-Apr-2026_Tue_21-50-13.954218": "InputManager.get_data() called for ['EEE_constants', 'constants'].",
  "14-Apr-2026_Tue_21-50-13.954687": "InputManager.get_data() called for ['EEE_constants', 'constants'].",
  "14-Apr-2026_Tue_21-50-13.954898": "InputManager.get_data() called for ['tractor_dataset'].",
  "14-Apr-2026_Tue_21-50-13.957552": "InputManager.get_data() called for ['EEE_constants', 'constants'].",
  "14-Apr-2026_Tue_21-50-13.958001": "InputManager.get_data() called for ['EEE_constants', 'constants'].",
  "14-Apr-2026_Tue_21-50-13.958263": "InputManager.get_data() called for ['tractor_dataset'].",
  "14-Apr-2026_Tue_21-50-13.960927": "InputManager.get_data() called for ['EEE_constants', 'constants'].",
  "14-Apr-2026_Tue_21-50-13.961513": "InputManager.get_data() called for ['EEE_constants', 'constants'].",
  "14-Apr-2026_Tue_21-50-13.961938": "InputManager.get_data() called for ['tractor_dataset'].",
  "14-Apr-2026_Tue_21-50-13.965206": "InputManager.get_data() called for ['EEE_constants', 'constants'].",
  "14-Apr-2026_Tue_21-50-13.965596": "InputManager.get_data() called for ['EEE_constants', 'constants'].",
  "14-Apr-2026_Tue_21-50-13.966041": "InputManager.get_data() called for ['tractor_dataset'].",
  "14-Apr-2026_Tue_21-50-13.969024": "InputManager.get_data() called for ['EEE_constants', 'constants'].",
  "14-Apr-2026_Tue_21-50-13.969456": "InputManager.get_data() called for ['EEE_constants', 'constants'].",
  "14-Apr-2026_Tue_21-50-13.969680": "InputManager.get_data() called for ['tractor_dataset'].",
  "14-Apr-2026_Tue_21-50-13.971848": "InputManager.get_data() called for ['EEE_constants', 'constants'].",
  "14-Apr-2026_Tue_21-50-13.972144": "InputManager.get_data() called for ['EEE_constants', 'constants'].",
  "14-Apr-2026_Tue_21-50-13.972432": "InputManager.get_data() called for ['tractor_dataset'].",
  "14-Apr-2026_Tue_21-50-13.974892": "InputManager.get_data() called for ['EEE_constants', 'constants'].",
  "14-Apr-2026_Tue_21-50-13.975234": "InputManager.get_data() called for ['EEE_constants', 'constants'].",
  "14-Apr-2026_Tue_21-50-13.975451": "InputManager.get_data() called for ['tractor_dataset'].",
  "14-Apr-2026_Tue_21-50-13.978520": "InputManager.get_data() called for ['EEE_constants', 'constants'].",
  "14-Apr-2026_Tue_21-50-13.978898": "InputManager.get_data() called for ['EEE_constants', 'constants'].",
  "14-Apr-2026_Tue_21-50-13.979169": "InputManager.get_data() called for ['tractor_dataset'].",
  "14-Apr-2026_Tue_21-50-13.981737": "InputManager.get_data() called for ['EEE_constants', 'constants'].",
  "14-Apr-2026_Tue_21-50-13.982076": "InputManager.get_data() called for ['EEE_constants', 'constants'].",
  "14-Apr-2026_Tue_21-50-13.982286": "InputManager.get_data() called for ['tractor_dataset'].",
  "14-Apr-2026_Tue_21-50-13.984441": "InputManager.get_data() called for ['EEE_constants', 'constants'].",
  "14-Apr-2026_Tue_21-50-13.985045": "InputManager.get_data() called for ['EEE_constants', 'constants'].",
  "14-Apr-2026_Tue_21-50-13.985464": "InputManager.get_data() called for ['tractor_dataset'].",
  "14-Apr-2026_Tue_21-50-13.989016": "InputManager.get_data() called for ['EEE_constants', 'constants'].",
  "14-Apr-2026_Tue_21-50-13.989602": "InputManager.get_data() called for ['EEE_constants', 'constants'].",
  "14-Apr-2026_Tue_21-50-13.990050": "InputManager.get_data() called for ['tractor_dataset'].",
  "14-Apr-2026_Tue_21-50-13.993330": "InputManager.get_data() called for ['EEE_constants', 'constants'].",
  "14-Apr-2026_Tue_21-50-13.993773": "InputManager.get_data() called for ['EEE_constants', 'constants'].",
  "14-Apr-2026_Tue_21-50-13.994017": "InputManager.get_data() called for ['tractor_dataset'].",
  "14-Apr-2026_Tue_21-50-13.996247": "InputManager.get_data() called for ['EEE_constants', 'constants'].",
  "14-Apr-2026_Tue_21-50-13.996592": "InputManager.get_data() called for ['EEE_constants', 'constants'].",
  "14-Apr-2026_Tue_21-50-13.996819": "InputManager.get_data() called for ['tractor_dataset'].",
  "14-Apr-2026_Tue_21-50-13.999031": "InputManager.get_data() called for ['EEE_constants', 'constants'].",
  "14-Apr-2026_Tue_21-50-13.999365": "InputManager.get_data() called for ['EEE_constants', 'constants'].",
  "14-Apr-2026_Tue_21-50-13.999559": "InputManager.get_data() called for ['tractor_dataset'].",
  "14-Apr-2026_Tue_21-50-14.001818": "InputManager.get_data() called for ['EEE_constants', 'constants'].",
  "14-Apr-2026_Tue_21-50-14.002165": "InputManager.get_data() called for ['EEE_constants', 'constants'].",
  "14-Apr-2026_Tue_21-50-14.002396": "InputManager.get_data() called for ['tractor_dataset'].",
  "14-Apr-2026_Tue_21-50-14.004646": "InputManager.get_data() called for ['EEE_constants', 'constants'].",
  "14-Apr-2026_Tue_21-50-14.005043": "InputManager.get_data() called for ['EEE_constants', 'constants'].",
  "14-Apr-2026_Tue_21-50-14.005295": "InputManager.get_data() called for ['tractor_dataset'].",
  "14-Apr-2026_Tue_21-50-14.007933": "InputManager.get_data() called for ['EEE_constants', 'constants'].",
  "14-Apr-2026_Tue_21-50-14.008382": "InputManager.get_data() called for ['EEE_constants', 'constants'].",
  "14-Apr-2026_Tue_21-50-14.008656": "InputManager.get_data() called for ['tractor_dataset'].",
  "14-Apr-2026_Tue_21-50-14.011107": "InputManager.get_data() called for ['EEE_constants', 'constants'].",
  "14-Apr-2026_Tue_21-50-14.011467": "InputManager.get_data() called for ['EEE_constants', 'constants'].",
  "14-Apr-2026_Tue_21-50-14.011696": "InputManager.get_data() called for ['tractor_dataset'].",
  "14-Apr-2026_Tue_21-50-14.014711": "InputManager.get_data() called for ['EEE_constants', 'constants'].",
  "14-Apr-2026_Tue_21-50-14.015023": "InputManager.get_data() called for ['EEE_constants', 'constants'].",
  "14-Apr-2026_Tue_21-50-14.015220": "InputManager.get_data() called for ['tractor_dataset'].",
  "14-Apr-2026_Tue_21-50-14.017469": "InputManager.get_data() called for ['EEE_constants', 'constants'].",
  "14-Apr-2026_Tue_21-50-14.017814": "InputManager.get_data() called for ['EEE_constants', 'constants'].",
  "14-Apr-2026_Tue_21-50-14.018050": "InputManager.get_data() called for ['tractor_dataset'].",
  "14-Apr-2026_Tue_21-50-14.020223": "InputManager.get_data() called for ['EEE_constants', 'constants'].",
  "14-Apr-2026_Tue_21-50-14.020540": "InputManager.get_data() called for ['EEE_constants', 'constants'].",
  "14-Apr-2026_Tue_21-50-14.020728": "InputManager.get_data() called for ['tractor_dataset'].",
  "14-Apr-2026_Tue_21-50-14.022637": "InputManager.get_data() called for ['EEE_constants', 'constants'].",
  "14-Apr-2026_Tue_21-50-14.022921": "InputManager.get_data() called for ['EEE_constants', 'constants'].",
  "14-Apr-2026_Tue_21-50-14.023122": "InputManager.get_data() called for ['tractor_dataset'].",
  "14-Apr-2026_Tue_21-50-14.024992": "InputManager.get_data() called for ['EEE_constants', 'constants'].",
  "14-Apr-2026_Tue_21-50-14.025266": "InputManager.get_data() called for ['EEE_constants', 'constants'].",
  "14-Apr-2026_Tue_21-50-14.025465": "InputManager.get_data() called for ['tractor_dataset'].",
  "14-Apr-2026_Tue_21-50-14.027666": "InputManager.get_data() called for ['EEE_constants', 'constants'].",
  "14-Apr-2026_Tue_21-50-14.027961": "InputManager.get_data() called for ['EEE_constants', 'constants'].",
  "14-Apr-2026_Tue_21-50-14.028172": "InputManager.get_data() called for ['tractor_dataset'].",
  "14-Apr-2026_Tue_21-50-14.030382": "InputManager.get_data() called for ['EEE_constants', 'constants'].",
  "14-Apr-2026_Tue_21-50-14.030688": "InputManager.get_data() called for ['EEE_constants', 'constants'].",
  "14-Apr-2026_Tue_21-50-14.030911": "InputManager.get_data() called for ['tractor_dataset'].",
  "14-Apr-2026_Tue_21-50-14.033074": "InputManager.get_data() called for ['EEE_constants', 'constants'].",
  "14-Apr-2026_Tue_21-50-14.033424": "InputManager.get_data() called for ['EEE_constants', 'constants'].",
  "14-Apr-2026_Tue_21-50-14.033645": "InputManager.get_data() called for ['tractor_dataset'].",
  "14-Apr-2026_Tue_21-50-14.035749": "InputManager.get_data() called for ['EEE_constants', 'constants'].",
  "14-Apr-2026_Tue_21-50-14.036054": "InputManager.get_data() called for ['EEE_constants', 'constants'].",
  "14-Apr-2026_Tue_21-50-14.036244": "InputManager.get_data() called for ['tractor_dataset'].",
  "14-Apr-2026_Tue_21-50-14.038306": "InputManager.get_data() called for ['EEE_constants', 'constants'].",
  "14-Apr-2026_Tue_21-50-14.038662": "InputManager.get_data() called for ['EEE_constants', 'constants'].",
  "14-Apr-2026_Tue_21-50-14.038859": "InputManager.get_data() called for ['tractor_dataset'].",
  "14-Apr-2026_Tue_21-50-14.040998": "InputManager.get_data() called for ['EEE_constants', 'constants'].",
  "14-Apr-2026_Tue_21-50-14.041330": "InputManager.get_data() called for ['EEE_constants', 'constants'].",
  "14-Apr-2026_Tue_21-50-14.041543": "InputManager.get_data() called for ['tractor_dataset'].",
  "14-Apr-2026_Tue_21-50-14.043629": "InputManager.get_data() called for ['EEE_constants', 'constants'].",
  "14-Apr-2026_Tue_21-50-14.043943": "InputManager.get_data() called for ['EEE_constants', 'constants'].",
  "14-Apr-2026_Tue_21-50-14.044145": "InputManager.get_data() called for ['tractor_dataset'].",
  "14-Apr-2026_Tue_21-50-14.046197": "InputManager.get_data() called for ['EEE_constants', 'constants'].",
  "14-Apr-2026_Tue_21-50-14.046513": "InputManager.get_data() called for ['EEE_constants', 'constants'].",
  "14-Apr-2026_Tue_21-50-14.046716": "InputManager.get_data() called for ['tractor_dataset'].",
  "14-Apr-2026_Tue_21-50-14.049075": "InputManager.get_data() called for ['EEE_constants', 'constants'].",
  "14-Apr-2026_Tue_21-50-14.049440": "InputManager.get_data() called for ['EEE_constants', 'constants'].",
  "14-Apr-2026_Tue_21-50-14.049655": "InputManager.get_data() called for ['tractor_dataset'].",
  "14-Apr-2026_Tue_21-50-14.051699": "InputManager.get_data() called for ['EEE_constants', 'constants'].",
  "14-Apr-2026_Tue_21-50-14.052067": "InputManager.get_data() called for ['EEE_constants', 'constants'].",
  "14-Apr-2026_Tue_21-50-14.052266": "InputManager.get_data() called for ['tractor_dataset'].",
  "14-Apr-2026_Tue_21-50-14.054229": "InputManager.get_data() called for ['EEE_constants', 'constants'].",
  "14-Apr-2026_Tue_21-50-14.054439": "InputManager.get_data() called for ['tractor_dataset'].",
  "14-Apr-2026_Tue_21-50-14.056516": "InputManager.get_data() called for ['EEE_constants', 'constants'].",
  "14-Apr-2026_Tue_21-50-14.056816": "InputManager.get_data() called for ['tractor_dataset'].",
  "14-Apr-2026_Tue_21-50-14.058907": "InputManager.get_data() called for ['EEE_constants', 'constants'].",
  "14-Apr-2026_Tue_21-50-14.059310": "InputManager.get_data() called for ['EEE_constants', 'constants'].",
  "14-Apr-2026_Tue_21-50-14.059524": "InputManager.get_data() called for ['tractor_dataset'].",
  "14-Apr-2026_Tue_21-50-14.061653": "InputManager.get_data() called for ['EEE_constants', 'constants'].",
  "14-Apr-2026_Tue_21-50-14.061900": "InputManager.get_data() called for ['tractor_dataset'].",
  "14-Apr-2026_Tue_21-50-14.064168": "InputManager.get_data() called for ['EEE_constants', 'constants'].",
  "14-Apr-2026_Tue_21-50-14.064419": "InputManager.get_data() called for ['tractor_dataset'].",
  "14-Apr-2026_Tue_21-50-14.066624": "InputManager.get_data() called for ['EEE_constants', 'constants'].",
  "14-Apr-2026_Tue_21-50-14.066994": "InputManager.get_data() called for ['EEE_constants', 'constants'].",
  "14-Apr-2026_Tue_21-50-14.067208": "InputManager.get_data() called for ['tractor_dataset'].",
  "14-Apr-2026_Tue_21-50-14.069337": "InputManager.get_data() called for ['EEE_constants', 'constants'].",
  "14-Apr-2026_Tue_21-50-14.069565": "InputManager.get_data() called for ['tractor_dataset'].",
  "14-Apr-2026_Tue_21-50-14.071752": "InputManager.get_data() called for ['EEE_constants', 'constants'].",
  "14-Apr-2026_Tue_21-50-14.071998": "InputManager.get_data() called for ['tractor_dataset'].",
  "14-Apr-2026_Tue_21-50-14.074058": "InputManager.get_data() called for ['EEE_constants', 'constants'].",
  "14-Apr-2026_Tue_21-50-14.074509": "InputManager.get_data() called for ['EEE_constants', 'constants'].",
  "14-Apr-2026_Tue_21-50-14.074729": "InputManager.get_data() called for ['tractor_dataset'].",
  "14-Apr-2026_Tue_21-50-14.076736": "InputManager.get_data() called for ['EEE_constants', 'constants'].",
  "14-Apr-2026_Tue_21-50-14.076945": "InputManager.get_data() called for ['tractor_dataset'].",
  "14-Apr-2026_Tue_21-50-14.078922": "InputManager.get_data() called for ['EEE_constants', 'constants'].",
  "14-Apr-2026_Tue_21-50-14.079146": "InputManager.get_data() called for ['tractor_dataset'].",
  "14-Apr-2026_Tue_21-50-14.081295": "InputManager.get_data() called for ['EEE_constants', 'constants'].",
  "14-Apr-2026_Tue_21-50-14.081639": "InputManager.get_data() called for ['EEE_constants', 'constants'].",
  "14-Apr-2026_Tue_21-50-14.081843": "InputManager.get_data() called for ['tractor_dataset'].",
  "14-Apr-2026_Tue_21-50-14.083831": "InputManager.get_data() called for ['EEE_constants', 'constants'].",
  "14-Apr-2026_Tue_21-50-14.084047": "InputManager.get_data() called for ['tractor_dataset'].",
  "14-Apr-2026_Tue_21-50-14.086063": "InputManager.get_data() called for ['EEE_constants', 'constants'].",
  "14-Apr-2026_Tue_21-50-14.086305": "InputManager.get_data() called for ['tractor_dataset'].",
  "14-Apr-2026_Tue_21-50-14.088313": "InputManager.get_data() called for ['EEE_constants', 'constants'].",
  "14-Apr-2026_Tue_21-50-14.088664": "InputManager.get_data() called for ['EEE_constants', 'constants'].",
  "14-Apr-2026_Tue_21-50-14.088871": "InputManager.get_data() called for ['tractor_dataset'].",
  "14-Apr-2026_Tue_21-50-14.090892": "InputManager.get_data() called for ['EEE_constants', 'constants'].",
  "14-Apr-2026_Tue_21-50-14.091118": "InputManager.get_data() called for ['tractor_dataset'].",
  "14-Apr-2026_Tue_21-50-14.093172": "InputManager.get_data() called for ['EEE_constants', 'constants'].",
  "14-Apr-2026_Tue_21-50-14.093392": "InputManager.get_data() called for ['tractor_dataset'].",
  "14-Apr-2026_Tue_21-50-14.095379": "InputManager.get_data() called for ['EEE_constants', 'constants'].",
  "14-Apr-2026_Tue_21-50-14.095698": "InputManager.get_data() called for ['EEE_constants', 'constants'].",
  "14-Apr-2026_Tue_21-50-14.095899": "InputManager.get_data() called for ['tractor_dataset'].",
  "14-Apr-2026_Tue_21-50-14.097966": "InputManager.get_data() called for ['EEE_constants', 'constants'].",
  "14-Apr-2026_Tue_21-50-14.098218": "InputManager.get_data() called for ['tractor_dataset'].",
  "14-Apr-2026_Tue_21-50-14.100358": "InputManager.get_data() called for ['EEE_constants', 'constants'].",
  "14-Apr-2026_Tue_21-50-14.100584": "InputManager.get_data() called for ['tractor_dataset'].",
  "14-Apr-2026_Tue_21-50-14.102607": "InputManager.get_data() called for ['EEE_constants', 'constants'].",
  "14-Apr-2026_Tue_21-50-14.102969": "InputManager.get_data() called for ['EEE_constants', 'constants'].",
  "14-Apr-2026_Tue_21-50-14.103178": "InputManager.get_data() called for ['tractor_dataset'].",
  "14-Apr-2026_Tue_21-50-14.105284": "InputManager.get_data() called for ['EEE_constants', 'constants'].",
  "14-Apr-2026_Tue_21-50-14.105514": "InputManager.get_data() called for ['tractor_dataset'].",
  "14-Apr-2026_Tue_21-50-14.107606": "InputManager.get_data() called for ['EEE_constants', 'constants'].",
  "14-Apr-2026_Tue_21-50-14.107827": "InputManager.get_data() called for ['tractor_dataset'].",
  "14-Apr-2026_Tue_21-50-14.109861": "InputManager.get_data() called for ['EEE_constants', 'constants'].",
  "14-Apr-2026_Tue_21-50-14.110198": "InputManager.get_data() called for ['EEE_constants', 'constants'].",
  "14-Apr-2026_Tue_21-50-14.110400": "InputManager.get_data() called for ['tractor_dataset'].",
  "14-Apr-2026_Tue_21-50-14.112379": "InputManager.get_data() called for ['EEE_constants', 'constants'].",
  "14-Apr-2026_Tue_21-50-14.112579": "InputManager.get_data() called for ['tractor_dataset'].",
  "14-Apr-2026_Tue_21-50-14.114570": "InputManager.get_data() called for ['EEE_constants', 'constants'].",
  "14-Apr-2026_Tue_21-50-14.114777": "InputManager.get_data() called for ['tractor_dataset'].",
  "14-Apr-2026_Tue_21-50-14.116741": "InputManager.get_data() called for ['EEE_constants', 'constants'].",
  "14-Apr-2026_Tue_21-50-14.117032": "InputManager.get_data() called for ['EEE_constants', 'constants'].",
  "14-Apr-2026_Tue_21-50-14.117231": "InputManager.get_data() called for ['tractor_dataset'].",
  "14-Apr-2026_Tue_21-50-14.119190": "InputManager.get_data() called for ['EEE_constants', 'constants'].",
  "14-Apr-2026_Tue_21-50-14.119387": "InputManager.get_data() called for ['tractor_dataset'].",
  "14-Apr-2026_Tue_21-50-14.121472": "InputManager.get_data() called for ['EEE_constants', 'constants'].",
  "14-Apr-2026_Tue_21-50-14.121707": "InputManager.get_data() called for ['tractor_dataset'].",
  "14-Apr-2026_Tue_21-50-14.123700": "InputManager.get_data() called for ['EEE_constants', 'constants'].",
  "14-Apr-2026_Tue_21-50-14.124041": "InputManager.get_data() called for ['EEE_constants', 'constants'].",
  "14-Apr-2026_Tue_21-50-14.124245": "InputManager.get_data() called for ['tractor_dataset'].",
  "14-Apr-2026_Tue_21-50-14.126236": "InputManager.get_data() called for ['EEE_constants', 'constants'].",
  "14-Apr-2026_Tue_21-50-14.126451": "InputManager.get_data() called for ['tractor_dataset'].",
  "14-Apr-2026_Tue_21-50-14.128414": "InputManager.get_data() called for ['EEE_constants', 'constants'].",
  "14-Apr-2026_Tue_21-50-14.128625": "InputManager.get_data() called for ['tractor_dataset'].",
  "14-Apr-2026_Tue_21-50-14.130604": "InputManager.get_data() called for ['EEE_constants', 'constants'].",
  "14-Apr-2026_Tue_21-50-14.130924": "InputManager.get_data() called for ['EEE_constants', 'constants'].",
  "14-Apr-2026_Tue_21-50-14.131129": "InputManager.get_data() called for ['tractor_dataset'].",
  "14-Apr-2026_Tue_21-50-14.133106": "InputManager.get_data() called for ['EEE_constants', 'constants'].",
  "14-Apr-2026_Tue_21-50-14.133319": "InputManager.get_data() called for ['tractor_dataset'].",
  "14-Apr-2026_Tue_21-50-14.135479": "InputManager.get_data() called for ['EEE_constants', 'constants'].",
  "14-Apr-2026_Tue_21-50-14.135735": "InputManager.get_data() called for ['tractor_dataset'].",
  "14-Apr-2026_Tue_21-50-14.137713": "InputManager.get_data() called for ['EEE_constants', 'constants'].",
  "14-Apr-2026_Tue_21-50-14.138048": "InputManager.get_data() called for ['EEE_constants', 'constants'].",
  "14-Apr-2026_Tue_21-50-14.138256": "InputManager.get_data() called for ['tractor_dataset'].",
  "14-Apr-2026_Tue_21-50-14.140242": "InputManager.get_data() called for ['EEE_constants', 'constants'].",
  "14-Apr-2026_Tue_21-50-14.140446": "InputManager.get_data() called for ['tractor_dataset'].",
  "14-Apr-2026_Tue_21-50-14.142412": "InputManager.get_data() called for ['EEE_constants', 'constants'].",
  "14-Apr-2026_Tue_21-50-14.142627": "InputManager.get_data() called for ['tractor_dataset'].",
  "14-Apr-2026_Tue_21-50-14.144605": "InputManager.get_data() called for ['EEE_constants', 'constants'].",
  "14-Apr-2026_Tue_21-50-14.144919": "InputManager.get_data() called for ['EEE_constants', 'constants'].",
  "14-Apr-2026_Tue_21-50-14.145119": "InputManager.get_data() called for ['tractor_dataset'].",
  "14-Apr-2026_Tue_21-50-14.147148": "InputManager.get_data() called for ['EEE_constants', 'constants'].",
  "14-Apr-2026_Tue_21-50-14.147436": "InputManager.get_data() called for ['tractor_dataset'].",
  "14-Apr-2026_Tue_21-50-14.149540": "InputManager.get_data() called for ['EEE_constants', 'constants'].",
  "14-Apr-2026_Tue_21-50-14.149793": "InputManager.get_data() called for ['tractor_dataset'].",
  "14-Apr-2026_Tue_21-50-14.151788": "InputManager.get_data() called for ['EEE_constants', 'constants'].",
  "14-Apr-2026_Tue_21-50-14.152180": "InputManager.get_data() called for ['EEE_constants', 'constants'].",
  "14-Apr-2026_Tue_21-50-14.152497": "InputManager.get_data() called for ['tractor_dataset'].",
  "14-Apr-2026_Tue_21-50-14.154707": "InputManager.get_data() called for ['EEE_constants', 'constants'].",
  "14-Apr-2026_Tue_21-50-14.154940": "InputManager.get_data() called for ['tractor_dataset'].",
  "14-Apr-2026_Tue_21-50-14.157026": "InputManager.get_data() called for ['EEE_constants', 'constants'].",
  "14-Apr-2026_Tue_21-50-14.157286": "InputManager.get_data() called for ['tractor_dataset'].",
  "14-Apr-2026_Tue_21-50-14.159430": "InputManager.get_data() called for ['EEE_constants', 'constants'].",
  "14-Apr-2026_Tue_21-50-14.159819": "InputManager.get_data() called for ['EEE_constants', 'constants'].",
  "14-Apr-2026_Tue_21-50-14.160050": "InputManager.get_data() called for ['tractor_dataset'].",
  "14-Apr-2026_Tue_21-50-14.162155": "InputManager.get_data() called for ['EEE_constants', 'constants'].",
  "14-Apr-2026_Tue_21-50-14.162402": "InputManager.get_data() called for ['tractor_dataset'].",
  "14-Apr-2026_Tue_21-50-14.164523": "InputManager.get_data() called for ['EEE_constants', 'constants'].",
  "14-Apr-2026_Tue_21-50-14.164759": "InputManager.get_data() called for ['tractor_dataset'].",
  "14-Apr-2026_Tue_21-50-14.167060": "InputManager.get_data() called for ['EEE_constants', 'constants'].",
  "14-Apr-2026_Tue_21-50-14.167480": "InputManager.get_data() called for ['EEE_constants', 'constants'].",
  "14-Apr-2026_Tue_21-50-14.167702": "InputManager.get_data() called for ['tractor_dataset'].",
  "14-Apr-2026_Tue_21-50-14.169681": "InputManager.get_data() called for ['EEE_constants', 'constants'].",
  "14-Apr-2026_Tue_21-50-14.169880": "InputManager.get_data() called for ['tractor_dataset'].",
  "14-Apr-2026_Tue_21-50-14.171856": "InputManager.get_data() called for ['EEE_constants', 'constants'].",
  "14-Apr-2026_Tue_21-50-14.172055": "InputManager.get_data() called for ['tractor_dataset'].",
  "14-Apr-2026_Tue_21-50-14.174019": "InputManager.get_data() called for ['EEE_constants', 'constants'].",
  "14-Apr-2026_Tue_21-50-14.174314": "InputManager.get_data() called for ['EEE_constants', 'constants'].",
  "14-Apr-2026_Tue_21-50-14.174521": "InputManager.get_data() called for ['tractor_dataset'].",
  "14-Apr-2026_Tue_21-50-14.176482": "InputManager.get_data() called for ['EEE_constants', 'constants'].",
  "14-Apr-2026_Tue_21-50-14.176681": "InputManager.get_data() called for ['tractor_dataset'].",
  "14-Apr-2026_Tue_21-50-14.178640": "InputManager.get_data() called for ['EEE_constants', 'constants'].",
  "14-Apr-2026_Tue_21-50-14.178848": "InputManager.get_data() called for ['tractor_dataset'].",
  "14-Apr-2026_Tue_21-50-14.180810": "InputManager.get_data() called for ['EEE_constants', 'constants'].",
  "14-Apr-2026_Tue_21-50-14.181102": "InputManager.get_data() called for ['EEE_constants', 'constants'].",
  "14-Apr-2026_Tue_21-50-14.181304": "InputManager.get_data() called for ['tractor_dataset'].",
  "14-Apr-2026_Tue_21-50-14.183296": "InputManager.get_data() called for ['EEE_constants', 'constants'].",
  "14-Apr-2026_Tue_21-50-14.183501": "InputManager.get_data() called for ['tractor_dataset'].",
  "14-Apr-2026_Tue_21-50-14.185834": "InputManager.get_data() called for ['EEE_constants', 'constants'].",
  "14-Apr-2026_Tue_21-50-14.186077": "InputManager.get_data() called for ['tractor_dataset'].",
  "14-Apr-2026_Tue_21-50-14.188211": "InputManager.get_data() called for ['EEE_constants', 'constants'].",
  "14-Apr-2026_Tue_21-50-14.188571": "InputManager.get_data() called for ['EEE_constants', 'constants'].",
  "14-Apr-2026_Tue_21-50-14.188805": "InputManager.get_data() called for ['tractor_dataset'].",
  "14-Apr-2026_Tue_21-50-14.190931": "InputManager.get_data() called for ['EEE_constants', 'constants'].",
  "14-Apr-2026_Tue_21-50-14.191237": "InputManager.get_data() called for ['EEE_constants', 'constants'].",
  "14-Apr-2026_Tue_21-50-14.191442": "InputManager.get_data() called for ['tractor_dataset'].",
  "14-Apr-2026_Tue_21-50-14.193480": "InputManager.get_data() called for ['EEE_constants', 'constants'].",
  "14-Apr-2026_Tue_21-50-14.193824": "InputManager.get_data() called for ['EEE_constants', 'constants'].",
  "14-Apr-2026_Tue_21-50-14.194029": "InputManager.get_data() called for ['tractor_dataset'].",
  "14-Apr-2026_Tue_21-50-14.196043": "InputManager.get_data() called for ['EEE_constants', 'constants'].",
  "14-Apr-2026_Tue_21-50-14.196382": "InputManager.get_data() called for ['EEE_constants', 'constants'].",
  "14-Apr-2026_Tue_21-50-14.196592": "InputManager.get_data() called for ['tractor_dataset'].",
  "14-Apr-2026_Tue_21-50-14.198761": "InputManager.get_data() called for ['EEE_constants', 'constants'].",
  "14-Apr-2026_Tue_21-50-14.199108": "InputManager.get_data() called for ['EEE_constants', 'constants'].",
  "14-Apr-2026_Tue_21-50-14.199311": "InputManager.get_data() called for ['tractor_dataset'].",
  "14-Apr-2026_Tue_21-50-14.201556": "InputManager.get_data() called for ['EEE_constants', 'constants'].",
  "14-Apr-2026_Tue_21-50-14.201906": "InputManager.get_data() called for ['EEE_constants', 'constants'].",
  "14-Apr-2026_Tue_21-50-14.202121": "InputManager.get_data() called for ['tractor_dataset'].",
  "14-Apr-2026_Tue_21-50-14.204154": "InputManager.get_data() called for ['EEE_constants', 'constants'].",
  "14-Apr-2026_Tue_21-50-14.204433": "InputManager.get_data() called for ['EEE_constants', 'constants'].",
  "14-Apr-2026_Tue_21-50-14.204637": "InputManager.get_data() called for ['tractor_dataset'].",
  "14-Apr-2026_Tue_21-50-14.206484": "InputManager.get_data() called for ['EEE_constants', 'constants'].",
  "14-Apr-2026_Tue_21-50-14.206736": "InputManager.get_data() called for ['EEE_constants', 'constants'].",
  "14-Apr-2026_Tue_21-50-14.206920": "InputManager.get_data() called for ['tractor_dataset'].",
  "14-Apr-2026_Tue_21-50-14.208733": "InputManager.get_data() called for ['EEE_constants', 'constants'].",
  "14-Apr-2026_Tue_21-50-14.208920": "InputManager.get_data() called for ['tractor_dataset'].",
  "14-Apr-2026_Tue_21-50-14.211371": "InputManager.get_data() called for ['EEE_constants', 'constants'].",
  "14-Apr-2026_Tue_21-50-14.211657": "InputManager.get_data() called for ['tractor_dataset'].",
  "14-Apr-2026_Tue_21-50-14.214128": "InputManager.get_data() called for ['EEE_constants', 'constants'].",
  "14-Apr-2026_Tue_21-50-14.214648": "InputManager.get_data() called for ['EEE_constants', 'constants'].",
  "14-Apr-2026_Tue_21-50-14.214855": "InputManager.get_data() called for ['tractor_dataset'].",
  "14-Apr-2026_Tue_21-50-14.216735": "InputManager.get_data() called for ['EEE_constants', 'constants'].",
  "14-Apr-2026_Tue_21-50-14.216919": "InputManager.get_data() called for ['tractor_dataset'].",
  "14-Apr-2026_Tue_21-50-14.218724": "InputManager.get_data() called for ['EEE_constants', 'constants'].",
  "14-Apr-2026_Tue_21-50-14.218918": "InputManager.get_data() called for ['tractor_dataset'].",
  "14-Apr-2026_Tue_21-50-14.220789": "InputManager.get_data() called for ['EEE_constants', 'constants'].",
  "14-Apr-2026_Tue_21-50-14.221076": "InputManager.get_data() called for ['EEE_constants', 'constants'].",
  "14-Apr-2026_Tue_21-50-14.221310": "InputManager.get_data() called for ['tractor_dataset'].",
  "14-Apr-2026_Tue_21-50-14.223303": "InputManager.get_data() called for ['EEE_constants', 'constants'].",
  "14-Apr-2026_Tue_21-50-14.223509": "InputManager.get_data() called for ['tractor_dataset'].",
  "14-Apr-2026_Tue_21-50-14.225474": "InputManager.get_data() called for ['EEE_constants', 'constants'].",
  "14-Apr-2026_Tue_21-50-14.225675": "InputManager.get_data() called for ['tractor_dataset'].",
  "14-Apr-2026_Tue_21-50-14.227643": "InputManager.get_data() called for ['EEE_constants', 'constants'].",
  "14-Apr-2026_Tue_21-50-14.227952": "InputManager.get_data() called for ['EEE_constants', 'constants'].",
  "14-Apr-2026_Tue_21-50-14.228152": "InputManager.get_data() called for ['tractor_dataset'].",
  "14-Apr-2026_Tue_21-50-14.230118": "InputManager.get_data() called for ['EEE_constants', 'constants'].",
  "14-Apr-2026_Tue_21-50-14.230318": "InputManager.get_data() called for ['tractor_dataset'].",
  "14-Apr-2026_Tue_21-50-14.232276": "InputManager.get_data() called for ['EEE_constants', 'constants'].",
  "14-Apr-2026_Tue_21-50-14.232475": "InputManager.get_data() called for ['tractor_dataset'].",
  "14-Apr-2026_Tue_21-50-14.234425": "InputManager.get_data() called for ['EEE_constants', 'constants'].",
  "14-Apr-2026_Tue_21-50-14.234750": "InputManager.get_data() called for ['EEE_constants', 'constants'].",
  "14-Apr-2026_Tue_21-50-14.234958": "InputManager.get_data() called for ['tractor_dataset'].",
  "14-Apr-2026_Tue_21-50-14.236927": "InputManager.get_data() called for ['EEE_constants', 'constants'].",
  "14-Apr-2026_Tue_21-50-14.237128": "InputManager.get_data() called for ['tractor_dataset'].",
  "14-Apr-2026_Tue_21-50-14.239092": "InputManager.get_data() called for ['EEE_constants', 'constants'].",
  "14-Apr-2026_Tue_21-50-14.239292": "InputManager.get_data() called for ['tractor_dataset'].",
  "14-Apr-2026_Tue_21-50-14.241234": "InputManager.get_data() called for ['EEE_constants', 'constants'].",
  "14-Apr-2026_Tue_21-50-14.241520": "InputManager.get_data() called for ['EEE_constants', 'constants'].",
  "14-Apr-2026_Tue_21-50-14.241719": "InputManager.get_data() called for ['tractor_dataset'].",
  "14-Apr-2026_Tue_21-50-14.243881": "InputManager.get_data() called for ['EEE_constants', 'constants'].",
  "14-Apr-2026_Tue_21-50-14.244139": "InputManager.get_data() called for ['tractor_dataset'].",
  "14-Apr-2026_Tue_21-50-14.246473": "InputManager.get_data() called for ['EEE_constants', 'constants'].",
  "14-Apr-2026_Tue_21-50-14.246730": "InputManager.get_data() called for ['tractor_dataset'].",
  "14-Apr-2026_Tue_21-50-14.248724": "InputManager.get_data() called for ['EEE_constants', 'constants'].",
  "14-Apr-2026_Tue_21-50-14.249080": "InputManager.get_data() called for ['EEE_constants', 'constants'].",
  "14-Apr-2026_Tue_21-50-14.249292": "InputManager.get_data() called for ['tractor_dataset'].",
  "14-Apr-2026_Tue_21-50-14.251320": "InputManager.get_data() called for ['EEE_constants', 'constants'].",
  "14-Apr-2026_Tue_21-50-14.251547": "InputManager.get_data() called for ['tractor_dataset'].",
  "14-Apr-2026_Tue_21-50-14.253638": "InputManager.get_data() called for ['EEE_constants', 'constants'].",
  "14-Apr-2026_Tue_21-50-14.253867": "InputManager.get_data() called for ['tractor_dataset'].",
  "14-Apr-2026_Tue_21-50-14.255906": "InputManager.get_data() called for ['EEE_constants', 'constants'].",
  "14-Apr-2026_Tue_21-50-14.256258": "InputManager.get_data() called for ['EEE_constants', 'constants'].",
  "14-Apr-2026_Tue_21-50-14.256460": "InputManager.get_data() called for ['tractor_dataset'].",
  "14-Apr-2026_Tue_21-50-14.258423": "InputManager.get_data() called for ['EEE_constants', 'constants'].",
  "14-Apr-2026_Tue_21-50-14.258624": "InputManager.get_data() called for ['tractor_dataset'].",
  "14-Apr-2026_Tue_21-50-14.260570": "InputManager.get_data() called for ['EEE_constants', 'constants'].",
  "14-Apr-2026_Tue_21-50-14.260768": "InputManager.get_data() called for ['tractor_dataset'].",
  "14-Apr-2026_Tue_21-50-14.262723": "InputManager.get_data() called for ['EEE_constants', 'constants'].",
  "14-Apr-2026_Tue_21-50-14.263010": "InputManager.get_data() called for ['EEE_constants', 'constants'].",
  "14-Apr-2026_Tue_21-50-14.263210": "InputManager.get_data() called for ['tractor_dataset'].",
  "14-Apr-2026_Tue_21-50-14.265150": "InputManager.get_data() called for ['EEE_constants', 'constants'].",
  "14-Apr-2026_Tue_21-50-14.265359": "InputManager.get_data() called for ['tractor_dataset'].",
  "14-Apr-2026_Tue_21-50-14.267309": "InputManager.get_data() called for ['EEE_constants', 'constants'].",
  "14-Apr-2026_Tue_21-50-14.267510": "InputManager.get_data() called for ['tractor_dataset'].",
  "14-Apr-2026_Tue_21-50-14.269456": "InputManager.get_data() called for ['EEE_constants', 'constants'].",
  "14-Apr-2026_Tue_21-50-14.269735": "InputManager.get_data() called for ['EEE_constants', 'constants'].",
  "14-Apr-2026_Tue_21-50-14.269934": "InputManager.get_data() called for ['tractor_dataset'].",
  "14-Apr-2026_Tue_21-50-14.271874": "InputManager.get_data() called for ['EEE_constants', 'constants'].",
  "14-Apr-2026_Tue_21-50-14.272081": "InputManager.get_data() called for ['tractor_dataset'].",
  "14-Apr-2026_Tue_21-50-14.274028": "InputManager.get_data() called for ['EEE_constants', 'constants'].",
  "14-Apr-2026_Tue_21-50-14.274227": "InputManager.get_data() called for ['tractor_dataset'].",
  "14-Apr-2026_Tue_21-50-14.276500": "InputManager.get_data() called for ['EEE_constants', 'constants'].",
  "14-Apr-2026_Tue_21-50-14.276878": "InputManager.get_data() called for ['EEE_constants', 'constants'].",
  "14-Apr-2026_Tue_21-50-14.277088": "InputManager.get_data() called for ['tractor_dataset'].",
  "14-Apr-2026_Tue_21-50-14.279189": "InputManager.get_data() called for ['EEE_constants', 'constants'].",
  "14-Apr-2026_Tue_21-50-14.279422": "InputManager.get_data() called for ['tractor_dataset'].",
  "14-Apr-2026_Tue_21-50-14.281503": "InputManager.get_data() called for ['EEE_constants', 'constants'].",
  "14-Apr-2026_Tue_21-50-14.281737": "InputManager.get_data() called for ['tractor_dataset'].",
  "14-Apr-2026_Tue_21-50-14.283714": "InputManager.get_data() called for ['EEE_constants', 'constants'].",
  "14-Apr-2026_Tue_21-50-14.284050": "InputManager.get_data() called for ['EEE_constants', 'constants'].",
  "14-Apr-2026_Tue_21-50-14.284253": "InputManager.get_data() called for ['tractor_dataset'].",
  "14-Apr-2026_Tue_21-50-14.286236": "InputManager.get_data() called for ['EEE_constants', 'constants'].",
  "14-Apr-2026_Tue_21-50-14.286492": "InputManager.get_data() called for ['EEE_constants', 'constants'].",
  "14-Apr-2026_Tue_21-50-14.286697": "InputManager.get_data() called for ['tractor_dataset'].",
  "14-Apr-2026_Tue_21-50-14.288645": "InputManager.get_data() called for ['EEE_constants', 'constants'].",
  "14-Apr-2026_Tue_21-50-14.288914": "InputManager.get_data() called for ['EEE_constants', 'constants'].",
  "14-Apr-2026_Tue_21-50-14.289123": "InputManager.get_data() called for ['tractor_dataset'].",
  "14-Apr-2026_Tue_21-50-14.290985": "InputManager.get_data() called for ['EEE_constants', 'constants'].",
  "14-Apr-2026_Tue_21-50-14.291213": "InputManager.get_data() called for ['EEE_constants', 'constants'].",
  "14-Apr-2026_Tue_21-50-14.291406": "InputManager.get_data() called for ['tractor_dataset'].",
  "14-Apr-2026_Tue_21-50-14.293276": "InputManager.get_data() called for ['EEE_constants', 'constants'].",
  "14-Apr-2026_Tue_21-50-14.293508": "InputManager.get_data() called for ['EEE_constants', 'constants'].",
  "14-Apr-2026_Tue_21-50-14.293697": "InputManager.get_data() called for ['tractor_dataset'].",
  "14-Apr-2026_Tue_21-50-14.295525": "InputManager.get_data() called for ['EEE_constants', 'constants'].",
  "14-Apr-2026_Tue_21-50-14.295787": "InputManager.get_data() called for ['EEE_constants', 'constants'].",
  "14-Apr-2026_Tue_21-50-14.295992": "InputManager.get_data() called for ['tractor_dataset'].",
  "14-Apr-2026_Tue_21-50-14.297943": "InputManager.get_data() called for ['EEE_constants', 'constants'].",
  "14-Apr-2026_Tue_21-50-14.298189": "InputManager.get_data() called for ['EEE_constants', 'constants'].",
  "14-Apr-2026_Tue_21-50-14.298386": "InputManager.get_data() called for ['tractor_dataset'].",
  "14-Apr-2026_Tue_21-50-14.300339": "InputManager.get_data() called for ['EEE_constants', 'constants'].",
  "14-Apr-2026_Tue_21-50-14.300576": "InputManager.get_data() called for ['EEE_constants', 'constants'].",
  "14-Apr-2026_Tue_21-50-14.300756": "InputManager.get_data() called for ['tractor_dataset'].",
  "14-Apr-2026_Tue_21-50-14.302558": "InputManager.get_data() called for ['EEE_constants', 'constants'].",
  "14-Apr-2026_Tue_21-50-14.302788": "InputManager.get_data() called for ['EEE_constants', 'constants'].",
  "14-Apr-2026_Tue_21-50-14.302967": "InputManager.get_data() called for ['tractor_dataset'].",
  "14-Apr-2026_Tue_21-50-14.304760": "InputManager.get_data() called for ['EEE_constants', 'constants'].",
  "14-Apr-2026_Tue_21-50-14.304991": "InputManager.get_data() called for ['EEE_constants', 'constants'].",
  "14-Apr-2026_Tue_21-50-14.305179": "InputManager.get_data() called for ['tractor_dataset'].",
  "14-Apr-2026_Tue_21-50-14.307133": "InputManager.get_data() called for ['EEE_constants', 'constants'].",
  "14-Apr-2026_Tue_21-50-14.307377": "InputManager.get_data() called for ['EEE_constants', 'constants'].",
  "14-Apr-2026_Tue_21-50-14.307573": "InputManager.get_data() called for ['tractor_dataset'].",
  "14-Apr-2026_Tue_21-50-14.309516": "InputManager.get_data() called for ['EEE_constants', 'constants']."
}